constec/py.typed
constec/db/__init__.py
constec/db/apps.py
constec/db/migrations/0001_initial.py
constec/db/migrations/0002_module_level.py
constec/db/migrations/0003_remove_module_level.py
constec/db/migrations/0004_rename_entities_company_cuit_idx_entities_company_e2c50f_idx_and_more.py
constec/db/migrations/__init__.py
constec/db/models/__init__.py
constec/db/models/base.py
constec/db/models/company.py
constec/db/models/contact.py
constec/db/models/erp.py
constec/db/models/erp_entity.py
constec/db/models/flow.py
constec/db/models/group.py
constec/db/models/module.py
constec/db/models/organization.py
constec/db/models/person.py
constec/db/models/session.py
constec/db/models/tag.py
constec/db/models/user.py
constec/services/__init__.py
constec/services/encryption.py
constec/shared/__init__.py
constec/shared/exceptions.py
constec/utils/__init__.py
constec/utils/cuit.py
constec/utils/password.py
constec-0.4.0.dist-info/licenses/LICENSE
constec-0.4.0.dist-info/METADATA
constec-0.4.0.dist-info/WHEEL
constec-0.4.0.dist-info/top_level.txt
constec-0.4.0.dist-info/RECORD
