Metadata-Version: 2.4
Name: constec
Version: 0.4.0
Summary: Base library for the Constec ecosystem - shared utilities, models, and namespace foundation
License: MIT
Project-URL: Homepage, https://github.com/TpmyCT/constec-python
Project-URL: Repository, https://github.com/TpmyCT/constec-python
Project-URL: Issues, https://github.com/TpmyCT/constec-python/issues
Classifier: Development Status :: 3 - Alpha
Classifier: Intended Audience :: Developers
Classifier: License :: OSI Approved :: MIT License
Classifier: Programming Language :: Python :: 3
Classifier: Programming Language :: Python :: 3.9
Classifier: Programming Language :: Python :: 3.10
Classifier: Programming Language :: Python :: 3.11
Classifier: Programming Language :: Python :: 3.12
Classifier: Typing :: Typed
Classifier: Framework :: Django :: 4.2
Requires-Python: >=3.9
License-File: LICENSE
Provides-Extra: db
Requires-Dist: Django>=4.2; extra == "db"
Provides-Extra: services
Requires-Dist: cryptography>=41.0; extra == "services"
Requires-Dist: bcrypt>=4.0; extra == "services"
Provides-Extra: utils
Requires-Dist: bcrypt>=4.0; extra == "utils"
Provides-Extra: all
Requires-Dist: constec[db,services,utils]; extra == "all"
Dynamic: license-file
